s1300257_learn/__init__.py
s1300257_learn-2024.7.30.dist-info/METADATA
s1300257_learn-2024.7.30.dist-info/WHEEL
s1300257_learn-2024.7.30.dist-info/top_level.txt
s1300257_learn-2024.7.30.dist-info/RECORD
